com_server/__init__.py
com_server/__main__.py
com_server/api_server.py
com_server/base_connection.py
com_server/connection.py
com_server/constants.py
com_server/disconnect.py
com_server/runner.py
com_server/tools.py
com_server/api/__init__.py
com_server/api/v0.py
com_server-0.1.4.dist-info/LICENSE
com_server-0.1.4.dist-info/METADATA
com_server-0.1.4.dist-info/WHEEL
com_server-0.1.4.dist-info/entry_points.txt
com_server-0.1.4.dist-info/top_level.txt
com_server-0.1.4.dist-info/RECORD
