Metadata-Version: 2.1
Name: com-server
Version: 0.1.4
Summary: A simple Python library and a REST API server that interacts with COM ports
Home-page: https://github.com/jonyboi396825/COM-Server
Author: Jonathan Liu
Author-email: jonathanhliu21@gmail.com
License: UNKNOWN
Platform: UNKNOWN
Classifier: Development Status :: 4 - Beta
Classifier: Intended Audience :: Developers
Classifier: License :: OSI Approved :: MIT License
Classifier: Operating System :: POSIX :: Linux
Classifier: Operating System :: MacOS :: MacOS X
Classifier: Operating System :: Microsoft :: Windows
Classifier: Programming Language :: Python :: 3
Classifier: Topic :: System :: Hardware :: Universal Serial Bus (USB)
Requires-Python: >=3.6
License-File: LICENSE
Requires-Dist: setuptools (>=58.5.3)
Requires-Dist: wheel (>=0.37.0)
Requires-Dist: pyserial (>=3.5)
Requires-Dist: flask-restful (>=0.3.9)
Requires-Dist: flask-cors (>=3.0.10)
Requires-Dist: docopt (>=0.6.2)
Requires-Dist: waitress (>=2.0.0)
